[
  {"id": "MH-MUM", "name": "Mumbai City", "stateId": "MH", "population": 3085411, "area": 157, "density": 19652, "literacyRate": 89.2, "sexRatio": 838, "headquarters": "Mumbai"},
  {"id": "MH-MUS", "name": "Mumbai Suburban", "stateId": "MH", "population": 9332481, "area": 446, "density": 20925, "literacyRate": 89.9, "sexRatio": 860, "headquarters": "Bandra"},
  {"id": "MH-THN", "name": "Thane", "stateId": "MH", "population": 11054131, "area": 4214, "density": 2623, "literacyRate": 84.5, "sexRatio": 886, "headquarters": "Thane"},
  {"id": "MH-PUN", "name": "Pune", "stateId": "MH", "population": 9426959, "area": 15643, "density": 603, "literacyRate": 87.2, "sexRatio": 915, "headquarters": "Pune"},
  {"id": "MH-NAG", "name": "Nagpur", "stateId": "MH", "population": 4653171, "area": 9892, "density": 470, "literacyRate": 88.3, "sexRatio": 951, "headquarters": "Nagpur"},
  {"id": "MH-NAS", "name": "Nashik", "stateId": "MH", "population": 6107187, "area": 15530, "density": 393, "literacyRate": 80.4, "sexRatio": 934, "headquarters": "Nashik"},
  {"id": "MH-AUR", "name": "Aurangabad", "stateId": "MH", "population": 3695928, "area": 10107, "density": 366, "literacyRate": 79.7, "sexRatio": 923, "headquarters": "Aurangabad"},
  {"id": "MH-AHM", "name": "Ahmednagar", "stateId": "MH", "population": 4543159, "area": 17048, "density": 266, "literacyRate": 78.0, "sexRatio": 939, "headquarters": "Ahmednagar"},
  {"id": "MH-SOL", "name": "Solapur", "stateId": "MH", "population": 4317756, "area": 14895, "density": 290, "literacyRate": 77.0, "sexRatio": 938, "headquarters": "Solapur"},
  {"id": "MH-KOL", "name": "Kolhapur", "stateId": "MH", "population": 3876001, "area": 7685, "density": 504, "literacyRate": 81.5, "sexRatio": 957, "headquarters": "Kolhapur"},
  {"id": "MH-SAT", "name": "Satara", "stateId": "MH", "population": 3003741, "area": 10480, "density": 287, "literacyRate": 82.9, "sexRatio": 988, "headquarters": "Satara"},
  {"id": "MH-SAN", "name": "Sangli", "stateId": "MH", "population": 2820575, "area": 8572, "density": 329, "literacyRate": 82.6, "sexRatio": 966, "headquarters": "Sangli"},
  {"id": "MH-RAT", "name": "Ratnagiri", "stateId": "MH", "population": 1612672, "area": 8208, "density": 196, "literacyRate": 82.4, "sexRatio": 1122, "headquarters": "Ratnagiri"},
  {"id": "MH-SIN", "name": "Sindhudurg", "stateId": "MH", "population": 849651, "area": 5207, "density": 163, "literacyRate": 85.6, "sexRatio": 1036, "headquarters": "Oros"},
  {"id": "MH-JLN", "name": "Jalna", "stateId": "MH", "population": 1958483, "area": 7694, "density": 254, "literacyRate": 71.5, "sexRatio": 937, "headquarters": "Jalna"},
  {"id": "MH-BID", "name": "Beed", "stateId": "MH", "population": 2585962, "area": 10693, "density": 242, "literacyRate": 73.5, "sexRatio": 916, "headquarters": "Beed"},
  {"id": "MH-LAT", "name": "Latur", "stateId": "MH", "population": 2455543, "area": 7157, "density": 343, "literacyRate": 77.3, "sexRatio": 928, "headquarters": "Latur"},
  {"id": "MH-OSM", "name": "Osmanabad", "stateId": "MH", "population": 1660311, "area": 7512, "density": 221, "literacyRate": 76.1, "sexRatio": 924, "headquarters": "Osmanabad"},
  {"id": "MH-NAN", "name": "Nanded", "stateId": "MH", "population": 3356566, "area": 10528, "density": 319, "literacyRate": 75.4, "sexRatio": 943, "headquarters": "Nanded"},
  {"id": "MH-PAR", "name": "Parbhani", "stateId": "MH", "population": 1836086, "area": 6511, "density": 282, "literacyRate": 74.0, "sexRatio": 947, "headquarters": "Parbhani"},
  {"id": "MH-HIN", "name": "Hingoli", "stateId": "MH", "population": 1178973, "area": 4524, "density": 261, "literacyRate": 74.5, "sexRatio": 942, "headquarters": "Hingoli"},
  {"id": "MH-AMR", "name": "Amravati", "stateId": "MH", "population": 2887826, "area": 12235, "density": 236, "literacyRate": 87.4, "sexRatio": 951, "headquarters": "Amravati"},
  {"id": "MH-AKO", "name": "Akola", "stateId": "MH", "population": 1813906, "area": 5428, "density": 334, "literacyRate": 86.9, "sexRatio": 946, "headquarters": "Akola"},
  {"id": "MH-WAS", "name": "Washim", "stateId": "MH", "population": 1197160, "area": 2897, "density": 413, "literacyRate": 83.0, "sexRatio": 930, "headquarters": "Washim"},
  {"id": "MH-BUL", "name": "Buldhana", "stateId": "MH", "population": 2588039, "area": 9661, "density": 268, "literacyRate": 83.7, "sexRatio": 934, "headquarters": "Buldhana"},
  {"id": "MH-YAV", "name": "Yavatmal", "stateId": "MH", "population": 2775457, "area": 13582, "density": 204, "literacyRate": 82.8, "sexRatio": 952, "headquarters": "Yavatmal"},
  {"id": "MH-WAR", "name": "Wardha", "stateId": "MH", "population": 1300774, "area": 6309, "density": 206, "literacyRate": 87.2, "sexRatio": 946, "headquarters": "Wardha"},
  {"id": "MH-BHA", "name": "Bhandara", "stateId": "MH", "population": 1200334, "area": 3717, "density": 323, "literacyRate": 85.0, "sexRatio": 982, "headquarters": "Bhandara"},
  {"id": "MH-GON", "name": "Gondia", "stateId": "MH", "population": 1322507, "area": 5431, "density": 244, "literacyRate": 85.4, "sexRatio": 999, "headquarters": "Gondia"},
  {"id": "MH-CHA", "name": "Chandrapur", "stateId": "MH", "population": 2204307, "area": 11443, "density": 193, "literacyRate": 80.0, "sexRatio": 961, "headquarters": "Chandrapur"},
  {"id": "MH-GAD", "name": "Gadchiroli", "stateId": "MH", "population": 1072942, "area": 14412, "density": 74, "literacyRate": 74.4, "sexRatio": 990, "headquarters": "Gadchiroli"},
  {"id": "MH-JLG", "name": "Jalgaon", "stateId": "MH", "population": 4224442, "area": 11765, "density": 359, "literacyRate": 78.3, "sexRatio": 925, "headquarters": "Jalgaon"},
  {"id": "MH-DHL", "name": "Dhule", "stateId": "MH", "population": 2048781, "area": 8063, "density": 254, "literacyRate": 74.6, "sexRatio": 944, "headquarters": "Dhule"},
  {"id": "MH-NAN2", "name": "Nandurbar", "stateId": "MH", "population": 1646177, "area": 5955, "density": 276, "literacyRate": 64.4, "sexRatio": 978, "headquarters": "Nandurbar"},
  {"id": "MH-RAI", "name": "Raigad", "stateId": "MH", "population": 2635394, "area": 7148, "density": 369, "literacyRate": 83.1, "sexRatio": 959, "headquarters": "Alibag"},
  {"id": "MH-PLG", "name": "Palghar", "stateId": "MH", "population": 2990116, "area": 5344, "density": 560, "literacyRate": 78.8, "sexRatio": 934, "headquarters": "Palghar"}
]

